Filter.v
module Filter(input CLK,
              input RST,
              input IN,
              output reg [7:0] OUT);
    
  reg [7:0] MEM [0:63];
  reg [7:0] VAL;
  reg [6:0] COUNT;
  reg [11:0] AVG;

  reg FLAG;

  reg V1;
  reg V2; //delayed by 1 clock
  reg V3; //delayed by 2 clocks

  integer i;

  //holds for calcs
  reg H2;

  //filter = x1-2x2+x3

  always @ (posedge CLK or negedge RST) begin
    if(RST == 0) begin
      FLAG <= 1'b0;
      VAL <= 0;
      V1 <= 0;
      V2 <= 0;
      V3 <= 0;
      H2 <= 0;
      COUNT <= 0;
      
      for (i = 0; i < 64; i=i+1) begin
        MEM[i] <= 0;
      end
    end
    else begin
      if(COUNT==63) begin
        V3 <= V2; // moving the values along the chain with 1 cycle delay
        V2 <= V1;
        V1 <= IN; // moving the values along the chain with 1 cycle delay
        FLAG <= 1'b1;
        COUNT <= 0;
      end
      else begin
        COUNT++;
      end
    end
  end

  always @ (V2) begin
    H2 <= (V2 << 1); //multiply by 2
  end

  always @ (V1 or H2 or V3) begin
    VAL <= (V1 - H2 + V3);
  end

  always @ (COUNT) begin
    i <= 0;
    MEM[COUNT] <= VAL; //using COUNT to iterate over array

    if (FLAG) begin
      AVG <= 0;
      for(i=0; i < 64; i = i + 1) begin
        AVG <= AVG + MEM[i];
      end

      OUT <= AVG >> 6;
    end
  end
endmodule

Filter_TB.v
// Testbench code for Filter & Decimator     64/44=16/11 //`time scale sets how long sim cycle lasts
module Filter_TB();
 
reg clk;
reg rst;
reg in;
reg [127:0] dataword;

wire [7:0]out;

Filter DUT(.CLK(clk),
          .RST(rst),
          .IN(in),
          .OUT(out));

initial
begin
   $dumpfile("dump.vcd");
        $dumpvars(1);
        clk<=0;
  rst=1;
  #10
  rst=0;
  #10
  rst=1;

// data upload 1    xxV0123456789ABC?
  dataword = 128'h02FF37abc326a7202381f0FF2a23f6be;
  #300
  dataword = 128'h3864292ae9600269F0FF73abc3b7a721;
  #300
  dataword = 128'h02395830aFF2a23FFbe3864792ae9603;
  #300
  dataword = 128'h312899abc02138698329aef923073785;
  #300
  dataword = 128'h0239830aFF2a23698329aef923073785;
  #10

  $finish;
end




always #5
begin
  clk <= ~clk;
end


always @(posedge clk)
begin
  in <= dataword[127];
  dataword <= { dataword[126:0],1'b0}; //left wise bit shifts
end



// module group2 group2_code(.clk (clk),
//                           .data (bitdata),
//                           .reset_n (reset_n),
//                           etc etc etc
//                                              )


endmodule

dump.vcd
$date
	Tue Apr 18 13:21:49 2023
$end
$version
	Icarus Verilog
$end
$timescale
	1s
$end
$scope module Filter_TB $end
$var wire 8 ! out [7:0] $end
$var reg 1 " clk $end
$var reg 128 # dataword [127:0] $end
$var reg 1 $ in $end
$var reg 1 % rst $end
$upscope $end
$enddefinitions $end
$comment Show the parameter values. $end
$dumpall
$end
#0
$dumpvars
1%
x$
bx #
0"
bx !
$end
#5
bx0 #
1"
#10
0"
0%
#15
bx00 #
1"
#20
0"
b10111111110011011110101011110000110010011010100111001000000010001110000001111100001111111100101010001000111111011010111110 #
1%
#25
b101111111100110111101010111100001100100110101001110010000000100011100000011111000011111111001010100010001111110110101111100 #
0$
1"
#30
0"
#35
b1011111111001101111010101111000011001001101010011100100000001000111000000111110000111111110010101000100011111101101011111000 #
1"
#40
0"
#45
b10111111110011011110101011110000110010011010100111001000000010001110000001111100001111111100101010001000111111011010111110000 #
1"
#50
0"
#55
b101111111100110111101010111100001100100110101001110010000000100011100000011111000011111111001010100010001111110110101111100000 #
1"
#60
0"
#65
b1011111111001101111010101111000011001001101010011100100000001000111000000111110000111111110010101000100011111101101011111000000 #
1"
#70
0"
#75
b10111111110011011110101011110000110010011010100111001000000010001110000001111100001111111100101010001000111111011010111110000000 #
1"
#80
0"
#85
b1111111100110111101010111100001100100110101001110010000000100011100000011111000011111111001010100010001111110110101111100000000 #
1$
1"
#90
0"
#95
b11111111001101111010101111000011001001101010011100100000001000111000000111110000111111110010101000100011111101101011111000000000 #
0$
1"
#100
0"
#105
b11111110011011110101011110000110010011010100111001000000010001110000001111100001111111100101010001000111111011010111110000000000 #
1$
1"
#110
0"
#115
b11111100110111101010111100001100100110101001110010000000100011100000011111000011111111001010100010001111110110101111100000000000 #
1"
#120
0"
#125
b11111001101111010101111000011001001101010011100100000001000111000000111110000111111110010101000100011111101101011111000000000000 #
1"
#130
0"
#135
b11110011011110101011110000110010011010100111001000000010001110000001111100001111111100101010001000111111011010111110000000000000 #
1"
#140
0"
#145
b11100110111101010111100001100100110101001110010000000100011100000011111000011111111001010100010001111110110101111100000000000000 #
1"
#150
0"
#155
b11001101111010101111000011001001101010011100100000001000111000000111110000111111110010101000100011111101101011111000000000000000 #
1"
#160
0"
#165
b10011011110101011110000110010011010100111001000000010001110000001111100001111111100101010001000111111011010111110000000000000000 #
1"
#170
0"
#175
b110111101010111100001100100110101001110010000000100011100000011111000011111111001010100010001111110110101111100000000000000000 #
1"
#180
0"
#185
b1101111010101111000011001001101010011100100000001000111000000111110000111111110010101000100011111101101011111000000000000000000 #
0$
1"
#190
0"
#195
b11011110101011110000110010011010100111001000000010001110000001111100001111111100101010001000111111011010111110000000000000000000 #
1"
#200
0"
#205
b10111101010111100001100100110101001110010000000100011100000011111000011111111001010100010001111110110101111100000000000000000000 #
1$
1"
#210
0"
#215
b1111010101111000011001001101010011100100000001000111000000111110000111111110010101000100011111101101011111000000000000000000000 #
1"
#220
0"
#225
b11110101011110000110010011010100111001000000010001110000001111100001111111100101010001000111111011010111110000000000000000000000 #
0$
1"
#230
0"
#235
b11101010111100001100100110101001110010000000100011100000011111000011111111001010100010001111110110101111100000000000000000000000 #
1$
1"
#240
0"
#245
b11010101111000011001001101010011100100000001000111000000111110000111111110010101000100011111101101011111000000000000000000000000 #
1"
#250
0"
#255
b10101011110000110010011010100111001000000010001110000001111100001111111100101010001000111111011010111110000000000000000000000000 #
1"
#260
0"
#265
b1010111100001100100110101001110010000000100011100000011111000011111111001010100010001111110110101111100000000000000000000000000 #
1"
#270
0"
#275
b10101111000011001001101010011100100000001000111000000111110000111111110010101000100011111101101011111000000000000000000000000000 #
0$
1"
#280
0"
#285
b1011110000110010011010100111001000000010001110000001111100001111111100101010001000111111011010111110000000000000000000000000000 #
1$
1"
#290
0"
#295
b10111100001100100110101001110010000000100011100000011111000011111111001010100010001111110110101111100000000000000000000000000000 #
0$
1"
#300
0"
#305
b1111000011001001101010011100100000001000111000000111110000111111110010101000100011111101101011111000000000000000000000000000000 #
1$
1"
#310
0"
#315
b11110000110010011010100111001000000010001110000001111100001111111100101010001000111111011010111110000000000000000000000000000000 #
0$
1"
#320
0"
b111000011001000010100100101010111010010110000000000010011010011111000011111111011100111010101111000011101101111010011100100001 #
#325
b1110000110010000101001001010101110100101100000000000100110100111110000111111110111001110101011110000111011011110100111001000010 #
1"
#330
0"
#335
b11100001100100001010010010101011101001011000000000001001101001111100001111111101110011101010111100001110110111101001110010000100 #
1"
#340
0"
#345
b11000011001000010100100101010111010010110000000000010011010011111000011111111011100111010101111000011101101111010011100100001000 #
1$
1"
#350
0"
#355
b10000110010000101001001010101110100101100000000000100110100111110000111111110111001110101011110000111011011110100111001000010000 #
1"
#360
0"
#365
b1100100001010010010101011101001011000000000001001101001111100001111111101110011101010111100001110110111101001110010000100000 #
1"
#370
0"
#375
b11001000010100100101010111010010110000000000010011010011111000011111111011100111010101111000011101101111010011100100001000000 #
0$
1"
#380
0"
#385
b110010000101001001010101110100101100000000000100110100111110000111111110111001110101011110000111011011110100111001000010000000 #
1"
#390
0"
#395
b1100100001010010010101011101001011000000000001001101001111100001111111101110011101010111100001110110111101001110010000100000000 #
1"
#400
0"
#405
b11001000010100100101010111010010110000000000010011010011111000011111111011100111010101111000011101101111010011100100001000000000 #
1"
#410
0"
#415
b10010000101001001010101110100101100000000000100110100111110000111111110111001110101011110000111011011110100111001000010000000000 #
1$
1"
#420
0"
#425
b100001010010010101011101001011000000000001001101001111100001111111101110011101010111100001110110111101001110010000100000000000 #
1"
#430
0"
#435
b1000010100100101010111010010110000000000010011010011111000011111111011100111010101111000011101101111010011100100001000000000000 #
0$
1"
#440
0"
#445
b10000101001001010101110100101100000000000100110100111110000111111110111001110101011110000111011011110100111001000010000000000000 #
1"
#450
0"
#455
b1010010010101011101001011000000000001001101001111100001111111101110011101010111100001110110111101001110010000100000000000000 #
1$
1"
#460
0"
#465
b10100100101010111010010110000000000010011010011111000011111111011100111010101111000011101101111010011100100001000000000000000 #
0$
1"
#470
0"
#475
b101001001010101110100101100000000000100110100111110000111111110111001110101011110000111011011110100111001000010000000000000000 #
1"
#480
0"
#485
b1010010010101011101001011000000000001001101001111100001111111101110011101010111100001110110111101001110010000100000000000000000 #
1"
#490
0"
#495
b10100100101010111010010110000000000010011010011111000011111111011100111010101111000011101101111010011100100001000000000000000000 #
1"
#500
0"
#505
b1001001010101110100101100000000000100110100111110000111111110111001110101011110000111011011110100111001000010000000000000000000 #
1$
1"
#510
0"
#515
b10010010101011101001011000000000001001101001111100001111111101110011101010111100001110110111101001110010000100000000000000000000 #
0$
1"
#520
0"
#525
b100101010111010010110000000000010011010011111000011111111011100111010101111000011101101111010011100100001000000000000000000000 #
1$
1"
#530
0"
#535
b1001010101110100101100000000000100110100111110000111111110111001110101011110000111011011110100111001000010000000000000000000000 #
0$
1"
#540
0"
#545
b10010101011101001011000000000001001101001111100001111111101110011101010111100001110110111101001110010000100000000000000000000000 #
1"
#550
0"
#555
b101010111010010110000000000010011010011111000011111111011100111010101111000011101101111010011100100001000000000000000000000000 #
1$
1"
#560
0"
#565
b1010101110100101100000000000100110100111110000111111110111001110101011110000111011011110100111001000010000000000000000000000000 #
0$
1"
#570
0"
#575
b10101011101001011000000000001001101001111100001111111101110011101010111100001110110111101001110010000100000000000000000000000000 #
1"
#580
0"
#585
b1010111010010110000000000010011010011111000011111111011100111010101111000011101101111010011100100001000000000000000000000000000 #
1$
1"
#590
0"
#595
b10101110100101100000000000100110100111110000111111110111001110101011110000111011011110100111001000010000000000000000000000000000 #
0$
1"
#600
0"
#605
b1011101001011000000000001001101001111100001111111101110011101010111100001110110111101001110010000100000000000000000000000000000 #
1$
1"
#610
0"
#615
b10111010010110000000000010011010011111000011111111011100111010101111000011101101111010011100100001000000000000000000000000000000 #
0$
1"
#620
0"
b10001110010101100000110000101011111111001010100010001111111111101111100011100001100100011110010010101011101001011000000011 #
#625
b100011100101011000001100001010111111110010101000100011111111111011111000111000011001000111100100101010111010010110000000110 #
1"
#630
0"
#635
b1000111001010110000011000010101111111100101010001000111111111110111110001110000110010001111001001010101110100101100000001100 #
1"
#640
0"
#645
b10001110010101100000110000101011111111001010100010001111111111101111100011100001100100011110010010101011101001011000000011000 #
1"
