Filter.v
module Filter(CLK,
            RST,
            IN,
            OUT);
    
input CLK;
input RST;
input IN;

output reg [7:0] OUT;

reg [7:0] MEM [0:63];
reg [7:0] VAL;
reg [7:0] COUNT;
reg [11:0] AVG;

reg FLAG;

reg V1;
reg V2; //delayed by 1 clock
reg V3; //delayed by 2 clocks

reg i;

//holds for calcs
reg H2;

//filter = x1-2x2+x3

always @(posedge CLK or negedge RST)
begin
    if(RST==0)
    begin
        FLAG <= 1'b0;
        VAL<=0;
        V1<=0;
        V2<=0;
        V3<=0;
        COUNT<=0;
        for (integer i = 0; i <=63; i++) 
        begin
            MEM[i] <= 0;
        end
    end
    else
    begin
        if(COUNT==63)
        begin
            V3<= V2; ///moving the values along the chain with 1 cycle delay
            V2<= V1;
            V1<= IN; ///moving the values along the chain with 1 cycle delay
            FLAG <= 1'b1;
            COUNT<=0;
        end
        else
        begin
            COUNT++;
        end
    end 

end

always@(V2)
begin
    H2<= (V2<<1); //multiply by 2
end

always@(V1 or H2 or V3)
begin
    VAL<=(V1-H2+V3);
end

always@ (COUNT)
begin
    i<=0;
    MEM[COUNT]<=VAL; //using COUNT to iterate over array


    if (FLAG) 
    begin
        AVG<=0;
        for(i=0;i<=63;i++)
        begin
            AVG<=AVG+MEM[i];
        end

        OUT<=AVG>>6;
    end
end

endmodule

Filter_TB.v
// Testbench code for Filter & Decimator     64/44=16/11 //`time scale sets how long sim cycle lasts
module Filter_TB();
 
reg clk;
reg rst;
reg in;
reg [127:0] dataword;

wire [7:0]out;

Filter DUT(.CLK(clk),
          .RST(rst),
          .IN(in),
          .OUT(out));

initial
begin
   $dumpfile("dump.vcd");
        $dumpvars(1);
        clk<=0;
  rst=1;
  #10
  rst=0;
  #10
  rst=1;

// data upload 1    xxV0123456789ABC?
  dataword = 128'h02FF37abc326a7202381f0FF2a23f6be;
  #10
  dataword = 128'h3864292ae9600269F0FF73abc3b7a721;
  #10
  dataword = 128'h02395830aFF2a23FFbe3864792ae9603;
  #10
  dataword = 128'h312899abc02138698329aef923073785;
  #10
  dataword = 128'h0239830aFF2a23698329aef923073785;
  #10

  $finish;
end




always #5
begin
  clk <= ~clk;
end


always @(posedge clk)
begin
  in <= dataword[127];
  dataword <= { dataword[126:0],1'b0}; //left wise bit shifts
end



// module group2 group2_code(.clk (clk),
//                           .data (bitdata),
//                           .reset_n (reset_n),
//                           etc etc etc
//                                              )


endmodule

dump.vcd
$date
	Fri Apr 07 11:55:11 2023
$end
$version
	Icarus Verilog
$end
$timescale
	1s
$end
$scope module Filter_TB $end
$var wire 8 ! out [7:0] $end
$var reg 1 " clk $end
$var reg 128 # dataword [127:0] $end
$var reg 1 $ in $end
$var reg 1 % rst $end
$upscope $end
$enddefinitions $end
$comment Show the parameter values. $end
$dumpall
$end
#0
$dumpvars
1%
x$
bx #
0"
bx !
$end
#5
bx0 #
1"
#10
0"
0%
#15
bx00 #
1"
#20
0"
b10111111110011011110101011110000110010011010100111001000000010001110000001111100001111111100101010001000111111011010111110 #
1%
#25
b101111111100110111101010111100001100100110101001110010000000100011100000011111000011111111001010100010001111110110101111100 #
0$
1"
#30
0"
b111000011001000010100100101010111010010110000000000010011010011111000011111111011100111010101111000011101101111010011100100001 #
#35
b1110000110010000101001001010101110100101100000000000100110100111110000111111110111001110101011110000111011011110100111001000010 #
1"
#40
0"
b10001110010101100000110000101011111111001010100010001111111111101111100011100001100100011110010010101011101001011000000011 #
#45
b100011100101011000001100001010111111110010101000100011111111111011111000111000011001000111100100101010111010010110000000110 #
1"
#50
0"
b110001001010001001100110101011110000000010000100111000011010011000001100101001101011101111100100100011000001110011011110000101 #
#55
b1100010010100010011001101010111100000000100001001110000110100110000011001010011010111011111001001000110000011100110111100001010 #
1"
#60
0"
b10001110011000001100001010111111110010101000100011011010011000001100101001101011101111100100100011000001110011011110000101 #
#65
b100011100110000011000010101111111100101010001000110110100110000011001010011010111011111001001000110000011100110111100001010 #
1"
