Filter.v
module Filter(input CLK,
              input RST,
              input IN,
              output reg [7:0] OUT);
 
  // Declaring the filter parameters
  parameter a0 = 1;
  parameter a1 = -2;
  parameter a2 = 1;
 
  // Declaring the circular averaging buffer
  parameter BUF_SIZE = 64;
  reg [7:0] buffer [0:BUF_SIZE-1];
  reg [6:0] buf_counter;
 
  // Downsampling counter
  reg [6:0] ds_counter;
 
  // Filter state variables
  reg [7:0] x;
  reg [7:0] y1;
  reg [7:0] y2;

  // Integer used for loops
  integer i;

  reg signed [9:0] sum;
  reg [7:0] avg;
 
  always @ (posedge CLK or negedge RST) begin
    if(RST == 0) begin
      // Reset output to 0
      OUT <= 0;
     
      // Reset the filter state variables
      y1 <= 0;
      y2 <= 0;
     
      // Reset the averaging buffer
      buf_counter <= 0;
      for (i = 0; i < BUF_SIZE; i=i+1) begin
        buffer[i] = 0;
      end
     
      // Reset the downsample counter
      ds_counter <= 0;
     
    end
    else begin
      // Filter the input sample and add it to the buffer
      x <= IN;
      buffer[buf_counter] = (IN + y2 > 2 * y1) ? IN - 2*y1 + y2 : 0;
      //OUT = buffer[buf_counter];
      // Update the filter state variables
      y2 <= y1;
      y1 <= x;
     
      // Increase the counter and reset to 0 if it gets to 64
      buf_counter <= (buf_counter == BUF_SIZE - 1) ? 0 : buf_counter + 1;
      
      // Compute the running average of the buffer
      sum = 0;
      for (i = 0; i < BUF_SIZE; i = i + 1) begin
        sum = sum + buffer[i];
      end
      // avg <= ((sum*10) / BUF_SIZE);
      if(((sum*10) / BUF_SIZE)<5) //avoids flooring when getting avg
        avg <= 0;
      else
        avg <= 1;
     
      // Downsample output by selecting one in every 64 samples
      ds_counter <= ds_counter + 1;
      if (ds_counter == 64) begin
        OUT <= avg;
        ds_counter <= 0;
      end else begin
        OUT <= 0;
      end
      
    end
  end
endmodule

Filter_TB.v
// Testbench code for Filter & Decimator     
module Filter_TB();
 
  reg clk;
  reg rst;
  reg in;
  reg [127:0] dataword;

  wire [7:0]out;

  Filter DUT(
    .CLK(clk),
    .RST(rst),
    .IN(in),
    .OUT(out)
  );

  initial begin
    
    $dumpfile("dump.vcd");
    $dumpvars(2);
    $monitor("%d", out);
    
  	clk = 1'b0;
    in = 1'b0;
    dataword = 0;
    
    //reset at start to set values
    rst = 1'b1;
    #100
    rst <= 1'b0;
    #100
    rst <= 1'b1;

    // data upload 1    xxV0123456789ABC?
    dataword = 128'h00000000000000000000000000000000; 
    #6425 //edge case ^
    dataword = 128'h02FF37abc326a7202381f0FF2a23f6be;
    #6425
    dataword = 128'h3864292ae9600269F0FF73abc3b7a721;
    #6425
    dataword = 128'h02395830aFF2a23FFbe3864792ae9603;
    #6425
    dataword = 128'h312899abc02138698329aef923073785;
    #6425
    dataword = 128'h0239830aFF2a23698329aef923073785;
    #6425 
    dataword = 128'hFFFFFFFFFFFFFFFFFFFFFFFFFFFFFFFF;
    #6425 //edge case ^

   $finish;
  end

  always #25
  begin
    clk <= ~clk;
  end
  
  // always #50
  // $display ("%d", in);

  always @(posedge clk) begin
    in <= dataword[127];
    dataword <= { dataword[126:0], 1'b0 }; //left wise bit shifts
    //$display ("in = %b", in);
  end
endmodule

dump.vcd
$date
	Thu Apr 27 17:33:12 2023
$end
$version
	Icarus Verilog
$end
$timescale
	1s
$end
$scope module Filter_TB $end
$var wire 8 ! out [7:0] $end
$var reg 1 " clk $end
$var reg 128 # dataword [127:0] $end
$var reg 1 $ in $end
$var reg 1 % rst $end
$scope module DUT $end
$var wire 1 " CLK $end
$var wire 1 $ IN $end
$var wire 1 % RST $end
$var parameter 32 & BUF_SIZE $end
$var parameter 32 ' a0 $end
$var parameter 32 ( a1 $end
$var parameter 32 ) a2 $end
$var reg 8 * OUT [7:0] $end
$var reg 8 + avg [7:0] $end
$var reg 7 , buf_counter [6:0] $end
$var reg 7 - ds_counter [6:0] $end
$var reg 10 . sum [9:0] $end
$var reg 8 / x [7:0] $end
$var reg 8 0 y1 [7:0] $end
$var reg 8 1 y2 [7:0] $end
$var integer 32 2 i [31:0] $end
$upscope $end
$upscope $end
$enddefinitions $end
$comment Show the parameter values. $end
$dumpall
b1 )
b11111111111111111111111111111110 (
b1 '
b1000000 &
$end
#0
$dumpvars
bx 2
bx 1
bx 0
bx /
bx .
bx -
bx ,
bx +
bx *
1%
0$
b0 #
0"
bx !
$end
#25
b0 !
b0 *
b1 +
b0 /
b1000000 2
bx .
1"
#50
0"
#75
b0 0
b1000000 2
bx .
1"
#100
b0 -
b0 ,
b0 1
b1000000 2
0"
0%
#125
b1000000 2
1"
#150
0"
#175
b1000000 2
1"
#200
0"
1%
#225
b1 -
b0 +
b1 ,
b1000000 2
b0 .
1"
#250
0"
#275
b10 -
b10 ,
b1000000 2
1"
#300
0"
#325
b11 -
b11 ,
b1000000 2
1"
#350
0"
#375
b100 -
b100 ,
b1000000 2
1"
#400
0"
#425
b101 -
b101 ,
b1000000 2
1"
#450
0"
#475
b110 -
b110 ,
b1000000 2
1"
#500
0"
#525
b111 -
b111 ,
b1000000 2
1"
#550
0"
#575
b1000 -
b1000 ,
b1000000 2
1"
#600
0"
#625
b1001 -
b1001 ,
b1000000 2
1"
#650
0"
#675
b1010 -
b1010 ,
b1000000 2
1"
#700
0"
#725
b1011 -
b1011 ,
b1000000 2
1"
#750
0"
#775
b1100 -
b1100 ,
b1000000 2
1"
#800
0"
#825
b1101 -
b1101 ,
b1000000 2
1"
#850
0"
#875
b1110 -
b1110 ,
b1000000 2
1"
#900
0"
#925
b1111 -
b1111 ,
b1000000 2
1"
#950
0"
#975
b10000 -
b10000 ,
b1000000 2
1"
#1000
0"
#1025
b10001 -
b10001 ,
b1000000 2
1"
#1050
0"
#1075
b10010 -
b10010 ,
b1000000 2
1"
#1100
0"
#1125
b10011 -
b10011 ,
b1000000 2
1"
#1150
0"
#1175
b10100 -
b10100 ,
b1000000 2
1"
#1200
0"
#1225
b10101 -
b10101 ,
b1000000 2
1"
#1250
0"
#1275
b10110 -
b10110 ,
b1000000 2
1"
#1300
0"
#1325
b10111 -
b10111 ,
b1000000 2
1"
#1350
0"
#1375
b11000 -
b11000 ,
b1000000 2
1"
#1400
0"
#1425
b11001 -
b11001 ,
b1000000 2
1"
#1450
0"
#1475
b11010 -
b11010 ,
b1000000 2
1"
#1500
0"
#1525
b11011 -
b11011 ,
b1000000 2
1"
#1550
0"
#1575
b11100 -
b11100 ,
b1000000 2
1"
#1600
0"
#1625
b11101 -
b11101 ,
b1000000 2
1"
#1650
0"
#1675
b11110 -
b11110 ,
b1000000 2
1"
#1700
0"
#1725
b11111 -
b11111 ,
b1000000 2
1"
#1750
0"
#1775
b100000 -
b100000 ,
b1000000 2
1"
#1800
0"
#1825
b100001 -
b100001 ,
b1000000 2
1"
#1850
0"
#1875
b100010 -
b100010 ,
b1000000 2
1"
#1900
0"
#1925
b100011 -
b100011 ,
b1000000 2
1"
#1950
0"
#1975
b100100 -
b100100 ,
b1000000 2
1"
#2000
0"
#2025
b100101 -
b100101 ,
b1000000 2
1"
#2050
0"
#2075
b100110 -
b100110 ,
b1000000 2
1"
#2100
0"
#2125
b100111 -
b100111 ,
b1000000 2
1"
#2150
0"
#2175
b101000 -
b101000 ,
b1000000 2
1"
#2200
0"
#2225
b101001 -
b101001 ,
b1000000 2
1"
#2250
0"
#2275
b101010 -
b101010 ,
b1000000 2
1"
#2300
0"
#2325
b101011 -
b101011 ,
b1000000 2
1"
#2350
0"
#2375
b101100 -
b101100 ,
b1000000 2
1"
#2400
0"
#2425
b101101 -
b101101 ,
b1000000 2
1"
#2450
0"
#2475
b101110 -
b101110 ,
b1000000 2
1"
#2500
0"
#2525
b101111 -
b101111 ,
b1000000 2
1"
#2550
0"
#2575
b110000 -
b110000 ,
b1000000 2
1"
#2600
0"
#2625
b110001 -
b110001 ,
b1000000 2
1"
#2650
0"
#2675
b110010 -
b110010 ,
b1000000 2
1"
#2700
0"
#2725
b110011 -
b110011 ,
b1000000 2
1"
#2750
0"
#2775
b110100 -
b110100 ,
b1000000 2
1"
#2800
0"
#2825
b110101 -
b110101 ,
b1000000 2
1"
#2850
0"
#2875
b110110 -
b110110 ,
b1000000 2
1"
#2900
0"
#2925
b110111 -
b110111 ,
b1000000 2
1"
#2950
0"
#2975
b111000 -
b111000 ,
b1000000 2
1"
#3000
0"
#3025
b111001 -
b111001 ,
b1000000 2
1"
#3050
0"
#3075
b111010 -
b111010 ,
b1000000 2
1"
#3100
0"
#3125
b111011 -
b111011 ,
b1000000 2
1"
#3150
0"
#3175
b111100 -
b111100 ,
b1000000 2
1"
#3200
0"
#3225
b111101 -
b111101 ,
b1000000 2
1"
#3250
0"
#3275
b111110 -
b111110 ,
b1000000 2
1"
#3300
0"
#3325
b111111 -
b111111 ,
b1000000 2
1"
#3350
0"
#3375
b1000000 -
b0 ,
b1000000 2
1"
#3400
0"
#3425
b0 -
b1 ,
b1000000 2
1"
#3450
0"
#3475
b1 -
b10 ,
b1000000 2
1"
#3500
0"
#3525
b10 -
b11 ,
b1000000 2
1"
#3550
0"
#3575
b11 -
b100 ,
b1000000 2
1"
#3600
0"
#3625
b100 -
b101 ,
b1000000 2
1"
#3650
0"
#3675
b101 -
b110 ,
b1000000 2
1"
#3700
0"
#3725
b110 -
b111 ,
b1000000 2
1"
#3750
0"
#3775
b111 -
b1000 ,
b1000000 2
1"
#3800
0"
#3825
b1000 -
b1001 ,
b1000000 2
1"
#3850
0"
#3875
b1001 -
b1010 ,
b1000000 2
1"
#3900
0"
#3925
b1010 -
b1011 ,
b1000000 2
1"
#3950
0"
#3975
b1011 -
b1100 ,
b1000000 2
1"
#4000
0"
#4025
b1100 -
b1101 ,
b1000000 2
1"
#4050
0"
#4075
b1101 -
b1110 ,
b1000000 2
1"
#4100
0"
#4125
b1110 -
b1111 ,
b1000000 2
1"
#4150
0"
#4175
b1111 -
b10000 ,
b1000000 2
1"
#4200
0"
#4225
b10000 -
b10001 ,
b1000000 2
1"
#4250
0"
#4275
b10001 -
b10010 ,
b1000000 2
1"
#4300
0"
#4325
b10010 -
b10011 ,
b1000000 2
1"
#4350
0"
#4375
b10011 -
b10100 ,
b1000000 2
1"
#4400
0"
#4425
b10100 -
b10101 ,
b1000000 2
1"
#4450
0"
#4475
b10101 -
b10110 ,
b1000000 2
1"
#4500
0"
#4525
b10110 -
b10111 ,
b1000000 2
1"
#4550
0"
#4575
b10111 -
b11000 ,
b1000000 2
1"
#4600
0"
#4625
b11000 -
b11001 ,
b1000000 2
1"
#4650
0"
#4675
b11001 -
b11010 ,
b1000000 2
1"
#4700
0"
#4725
b11010 -
b11011 ,
b1000000 2
1"
#4750
0"
#4775
b11011 -
b11100 ,
b1000000 2
1"
#4800
0"
#4825
b11100 -
b11101 ,
b1000000 2
1"
#4850
0"
#4875
b11101 -
b11110 ,
b1000000 2
1"
#4900
0"
#4925
b11110 -
b11111 ,
b1000000 2
1"
#4950
0"
#4975
b11111 -
b100000 ,
b1000000 2
1"
#5000
0"
#5025
b100000 -
b100001 ,
b1000000 2
1"
#5050
0"
#5075
b100001 -
b100010 ,
b1000000 2
1"
#5100
0"
#5125
b100010 -
b100011 ,
b1000000 2
1"
#5150
0"
#5175
b100011 -
b100100 ,
b1000000 2
1"
#5200
0"
#5225
b100100 -
b100101 ,
b1000000 2
1"
#5250
0"
#5275
b100101 -
b100110 ,
b1000000 2
1"
#5300
0"
#5325
b100110 -
b100111 ,
b1000000 2
1"
#5350
0"
#5375
b100111 -
b101000 ,
b1000000 2
1"
#5400
0"
#5425
b101000 -
b101001 ,
b1000000 2
1"
#5450
0"
#5475
b101001 -
b101010 ,
b1000000 2
1"
#5500
0"
#5525
b101010 -
b101011 ,
b1000000 2
1"
#5550
0"
#5575
b101011 -
b101100 ,
b1000000 2
1"
#5600
0"
#5625
b101100 -
b101101 ,
b1000000 2
1"
#5650
0"
#5675
b101101 -
b101110 ,
b1000000 2
1"
#5700
0"
#5725
b101110 -
b101111 ,
b1000000 2
1"
#5750
0"
#5775
b101111 -
b110000 ,
b1000000 2
1"
#5800
0"
#5825
b110000 -
b110001 ,
b1000000 2
1"
#5850
0"
#5875
b110001 -
b110010 ,
b1000000 2
1"
#5900
0"
#5925
b110010 -
b110011 ,
b1000000 2
1"
#5950
0"
#5975
b110011 -
b110100 ,
b1000000 2
1"
#6000
0"
#6025
b110100 -
b110101 ,
b1000000 2
1"
#6050
0"
#6075
b110101 -
b110110 ,
b1000000 2
1"
#6100
0"
#6125
b110110 -
b110111 ,
b1000000 2
1"
#6150
0"
#6175
b110111 -
b111000 ,
b1000000 2
1"
#6200
0"
#6225
b111000 -
b111001 ,
b1000000 2
1"
#6250
0"
#6275
b111001 -
b111010 ,
b1000000 2
1"
#6300
0"
#6325
b111010 -
b111011 ,
b1000000 2
1"
#6350
0"
#6375
b111011 -
b111100 ,
b1000000 2
1"
#6400
0"
#6425
b111100 -
b111101 ,
b1000000 2
1"
#6450
0"
#6475
b111101 -
b111110 ,
b1000000 2
1"
#6500
0"
#6525
b111110 -
b111111 ,
b1000000 2
1"
#6550
0"
#6575
b111111 -
b0 ,
b1000000 2
1"
#6600
0"
#6625
b1000000 -
b1 ,
b1000000 2
1"
b101111111100110111101010111100001100100110101001110010000000100011100000011111000011111111001010100010001111110110101111100 #
#6650
0"
#6675
b0 -
b10 ,
b1011111111001101111010101111000011001001101010011100100000001000111000000111110000111111110010101000100011111101101011111000 #
b1000000 2
1"
#6700
0"
#6725
b1 -
b11 ,
b10111111110011011110101011110000110010011010100111001000000010001110000001111100001111111100101010001000111111011010111110000 #
b1000000 2
1"
#6750
0"
#6775
b10 -
b100 ,
b101111111100110111101010111100001100100110101001110010000000100011100000011111000011111111001010100010001111110110101111100000 #
b1000000 2
1"
#6800
0"
#6825
b11 -
b101 ,
b1011111111001101111010101111000011001001101010011100100000001000111000000111110000111111110010101000100011111101101011111000000 #
b1000000 2
1"
#6850
0"
#6875
b100 -
b110 ,
b10111111110011011110101011110000110010011010100111001000000010001110000001111100001111111100101010001000111111011010111110000000 #
b1000000 2
1"
#6900
0"
#6925
b101 -
b111 ,
b1111111100110111101010111100001100100110101001110010000000100011100000011111000011111111001010100010001111110110101111100000000 #
1$
b1000000 2
1"
#6950
0"
#6975
b110 -
b1000 ,
b1 /
b11111111001101111010101111000011001001101010011100100000001000111000000111110000111111110010101000100011111101101011111000000000 #
0$
b1 .
b1000000 2
1"
#7000
0"
#7025
b111 -
b1001 ,
b1 0
b0 /
b11111110011011110101011110000110010011010100111001000000010001110000001111100001111111100101010001000111111011010111110000000000 #
1$
b1000000 2
b1 .
1"
#7050
0"
#7075
b1000 -
b1010 ,
b0 0
b1 1
b1 /
b11111100110111101010111100001100100110101001110010000000100011100000011111000011111111001010100010001111110110101111100000000000 #
b1000000 2
b1 .
1"
#7100
0"
#7125
b1001 -
b1011 ,
b1 0
b0 1
b11111001101111010101111000011001001101010011100100000001000111000000111110000111111110010101000100011111101101011111000000000000 #
b1000000 2
b11 .
1"
#7150
0"
#7175
b1010 -
b1100 ,
b1 1
b11110011011110101011110000110010011010100111001000000010001110000001111100001111111100101010001000111111011010111110000000000000 #
b1000000 2
b11 .
1"
#7200
0"
#7225
b1011 -
b1101 ,
b11100110111101010111100001100100110101001110010000000100011100000011111000011111111001010100010001111110110101111100000000000000 #
b1000000 2
b11 .
1"
#7250
0"
#7275
b1100 -
b1110 ,
b11001101111010101111000011001001101010011100100000001000111000000111110000111111110010101000100011111101101011111000000000000000 #
b1000000 2
b11 .
1"
#7300
0"
#7325
b1101 -
b1111 ,
b10011011110101011110000110010011010100111001000000010001110000001111100001111111100101010001000111111011010111110000000000000000 #
b1000000 2
b11 .
1"
#7350
0"
#7375
b1110 -
b10000 ,
b110111101010111100001100100110101001110010000000100011100000011111000011111111001010100010001111110110101111100000000000000000 #
b1000000 2
b11 .
1"
#7400
0"
#7425
b1111 -
b10001 ,
b1101111010101111000011001001101010011100100000001000111000000111110000111111110010101000100011111101101011111000000000000000000 #
0$
b1000000 2
b11 .
1"
#7450
0"
#7475
b10000 -
b10010 ,
b0 /
b11011110101011110000110010011010100111001000000010001110000001111100001111111100101010001000111111011010111110000000000000000000 #
b1000000 2
b11 .
1"
#7500
0"
#7525
b10001 -
b10011 ,
b0 0
b10111101010111100001100100110101001110010000000100011100000011111000011111111001010100010001111110110101111100000000000000000000 #
1$
b1000000 2
b11 .
1"
#7550
0"
#7575
b10010 -
b10100 ,
b0 1
b1 /
b1111010101111000011001001101010011100100000001000111000000111110000111111110010101000100011111101101011111000000000000000000000 #
b1000000 2
b101 .
1"
#7600
0"
#7625
b10011 -
b10101 ,
b1 0
b11110101011110000110010011010100111001000000010001110000001111100001111111100101010001000111111011010111110000000000000000000000 #
0$
b1000000 2
b110 .
1"
#7650
0"
#7675
b10100 -
b10110 ,
b1 1
b0 /
b11101010111100001100100110101001110010000000100011100000011111000011111111001010100010001111110110101111100000000000000000000000 #
1$
b1000000 2
b110 .
1"
#7700
0"
#7725
b10101 -
b10111 ,
b0 0
b1 /
b11010101111000011001001101010011100100000001000111000000111110000111111110010101000100011111101101011111000000000000000000000000 #
b1000000 2
b110 .
1"
#7750
0"
#7775
b10110 -
b11000 ,
b1 0
b0 1
b10101011110000110010011010100111001000000010001110000001111100001111111100101010001000111111011010111110000000000000000000000000 #
b1000000 2
b1000 .
1"
#7800
0"
#7825
b10111 -
b11001 ,
b1 1
b1010111100001100100110101001110010000000100011100000011111000011111111001010100010001111110110101111100000000000000000000000000 #
b1000000 2
b1000 .
1"
#7850
0"
#7875
b11000 -
b11010 ,
b10101111000011001001101010011100100000001000111000000111110000111111110010101000100011111101101011111000000000000000000000000000 #
0$
b1000000 2
b1000 .
1"
#7900
0"
#7925
b11001 -
b11011 ,
b0 /
b1011110000110010011010100111001000000010001110000001111100001111111100101010001000111111011010111110000000000000000000000000000 #
1$
b1000000 2
b1000 .
1"
#7950
0"
#7975
b11010 -
b11100 ,
b0 0
b1 /
b10111100001100100110101001110010000000100011100000011111000011111111001010100010001111110110101111100000000000000000000000000000 #
0$
b1000000 2
b1000 .
1"
#8000
0"
#8025
b11011 -
b11101 ,
b1 0
b0 1
b0 /
b1111000011001001101010011100100000001000111000000111110000111111110010101000100011111101101011111000000000000000000000000000000 #
1$
b1000000 2
b1001 .
1"
#8050
0"
#8075
b11100 -
b11110 ,
b0 0
b1 1
b1 /
b11110000110010011010100111001000000010001110000001111100001111111100101010001000111111011010111110000000000000000000000000000000 #
0$
b1000000 2
b1001 .
1"
#8100
0"
#8125
b11101 -
b11111 ,
b1 0
b0 1
b0 /
b11100001100100110101001110010000000100011100000011111000011111111001010100010001111110110101111100000000000000000000000000000000 #
1$
b1000000 2
b1010 .
1"
#8150
0"
#8175
b11110 -
b100000 ,
b0 0
b1 1
b1 /
b11000011001001101010011100100000001000111000000111110000111111110010101000100011111101101011111000000000000000000000000000000000 #
b1000000 2
b1010 .
1"
#8200
0"
#8225
b11111 -
b100001 ,
b1 0
b0 1
b10000110010011010100111001000000010001110000001111100001111111100101010001000111111011010111110000000000000000000000000000000000 #
b1000000 2
b1100 .
1"
#8250
0"
#8275
b100000 -
b100010 ,
b1 1
b1100100110101001110010000000100011100000011111000011111111001010100010001111110110101111100000000000000000000000000000000000 #
b1000000 2
b1100 .
1"
#8300
0"
#8325
b100001 -
b100011 ,
b11001001101010011100100000001000111000000111110000111111110010101000100011111101101011111000000000000000000000000000000000000 #
0$
b1000000 2
b1100 .
1"
#8350
0"
#8375
b100010 -
b100100 ,
b0 /
b110010011010100111001000000010001110000001111100001111111100101010001000111111011010111110000000000000000000000000000000000000 #
b1000000 2
b1100 .
1"
#8400
0"
#8425
b100011 -
b100101 ,
b0 0
b1100100110101001110010000000100011100000011111000011111111001010100010001111110110101111100000000000000000000000000000000000000 #
b1000000 2
b1100 .
1"
#8450
0"
#8475
b100100 -
b100110 ,
b0 1
b11001001101010011100100000001000111000000111110000111111110010101000100011111101101011111000000000000000000000000000000000000000 #
b1000000 2
b1101 .
1"
#8500
0"
#8525
b100101 -
b100111 ,
b10010011010100111001000000010001110000001111100001111111100101010001000111111011010111110000000000000000000000000000000000000000 #
1$
b1000000 2
b1101 .
1"
#8550
0"
#8575
b100110 -
b101000 ,
b1 /
b100110101001110010000000100011100000011111000011111111001010100010001111110110101111100000000000000000000000000000000000000000 #
b1000000 2
b1110 .
1"
#8600
0"
#8625
b100111 -
b101001 ,
b1 0
b1001101010011100100000001000111000000111110000111111110010101000100011111101101011111000000000000000000000000000000000000000000 #
0$
b1000000 2
b1111 .
1"
#8650
0"
#8675
b101000 -
b101010 ,
b1 1
b0 /
b10011010100111001000000010001110000001111100001111111100101010001000111111011010111110000000000000000000000000000000000000000000 #
b1000000 2
b1111 .
1"
#8700
0"
#8725
b101001 -
b101011 ,
b0 0
b110101001110010000000100011100000011111000011111111001010100010001111110110101111100000000000000000000000000000000000000000000 #
1$
b1000000 2
b1111 .
1"
#8750
0"
#8775
b101010 -
b101100 ,
b0 1
b1 /
b1101010011100100000001000111000000111110000111111110010101000100011111101101011111000000000000000000000000000000000000000000000 #
0$
b1000000 2
b10001 .
1"
#8800
0"
#8825
b101011 -
b101101 ,
b1 0
b0 /
b11010100111001000000010001110000001111100001111111100101010001000111111011010111110000000000000000000000000000000000000000000000 #
b1000000 2
b10001 .
1"
#8850
0"
#8875
b101100 -
b101110 ,
b0 0
b1 1
b10101001110010000000100011100000011111000011111111001010100010001111110110101111100000000000000000000000000000000000000000000000 #
1$
b1000000 2
b10001 .
1"
#8900
0"
#8925
b101101 -
b101111 ,
b0 1
b1 /
b1010011100100000001000111000000111110000111111110010101000100011111101101011111000000000000000000000000000000000000000000000000 #
b1000000 2
b10011 .
1"
#8950
0"
#8975
b101110 -
b110000 ,
b1 0
b10100111001000000010001110000001111100001111111100101010001000111111011010111110000000000000000000000000000000000000000000000000 #
0$
b1000000 2
b10100 .
1"
#9000
0"
#9025
b101111 -
b110001 ,
b1 1
b0 /
b1001110010000000100011100000011111000011111111001010100010001111110110101111100000000000000000000000000000000000000000000000000 #
1$
b1000000 2
b10100 .
1"
#9050
0"
#9075
b110000 -
b110010 ,
b0 0
b1 /
b10011100100000001000111000000111110000111111110010101000100011111101101011111000000000000000000000000000000000000000000000000000 #
0$
b1000000 2
b10100 .
1"
#9100
0"
#9125
b110001 -
b110011 ,
b1 0
b0 1
b0 /
b111001000000010001110000001111100001111111100101010001000111111011010111110000000000000000000000000000000000000000000000000000 #
1$
b1000000 2
b10101 .
1"
#9150
0"
#9175
b110010 -
b110100 ,
b0 0
b1 1
b1 /
b1110010000000100011100000011111000011111111001010100010001111110110101111100000000000000000000000000000000000000000000000000000 #
0$
b1000000 2
b10101 .
1"
#9200
0"
#9225
b110011 -
b110101 ,
b1 0
b0 1
b0 /
b11100100000001000111000000111110000111111110010101000100011111101101011111000000000000000000000000000000000000000000000000000000 #
b1000000 2
b10110 .
1"
#9250
0"
#9275
b110100 -
b110110 ,
b0 0
b1 1
b11001000000010001110000001111100001111111100101010001000111111011010111110000000000000000000000000000000000000000000000000000000 #
1$
b1000000 2
b10110 .
1"
#9300
0"
#9325
b110101 -
b110111 ,
b0 1
b1 /
b10010000000100011100000011111000011111111001010100010001111110110101111100000000000000000000000000000000000000000000000000000000 #
b1000000 2
b11000 .
1"
#9350
0"
#9375
b110110 -
b111000 ,
b1 0
b100000001000111000000111110000111111110010101000100011111101101011111000000000000000000000000000000000000000000000000000000000 #
b1000000 2
b11001 .
1"
#9400
0"
#9425
b110111 -
b111001 ,
b1 1
b1000000010001110000001111100001111111100101010001000111111011010111110000000000000000000000000000000000000000000000000000000000 #
0$
b1000000 2
b11001 .
1"
#9450
0"
#9475
b111000 -
b111010 ,
b0 /
b10000000100011100000011111000011111111001010100010001111110110101111100000000000000000000000000000000000000000000000000000000000 #
b1000000 2
b11001 .
1"
#9500
0"
#9525
b111001 -
b111011 ,
b0 0
b1000111000000111110000111111110010101000100011111101101011111000000000000000000000000000000000000000000000000000000000000 #
1$
b1000000 2
b11001 .
1"
#9550
0"
#9575
b111010 -
b111100 ,
b0 1
b1 /
b10001110000001111100001111111100101010001000111111011010111110000000000000000000000000000000000000000000000000000000000000 #
0$
b1000000 2
b11011 .
1"
#9600
0"
#9625
b111011 -
b111101 ,
b1 0
b0 /
b100011100000011111000011111111001010100010001111110110101111100000000000000000000000000000000000000000000000000000000000000 #
b1000000 2
b11011 .
1"
#9650
0"
#9675
b111100 -
b111110 ,
b0 0
b1 1
b1000111000000111110000111111110010101000100011111101101011111000000000000000000000000000000000000000000000000000000000000000 #
b1000000 2
b11011 .
1"
#9700
0"
#9725
b111101 -
b111111 ,
b0 1
b10001110000001111100001111111100101010001000111111011010111110000000000000000000000000000000000000000000000000000000000000000 #
b1000000 2
b11100 .
1"
#9750
0"
#9775
b111110 -
b0 ,
b100011100000011111000011111111001010100010001111110110101111100000000000000000000000000000000000000000000000000000000000000000 #
b1000000 2
b11100 .
1"
#9800
0"
#9825
b111111 -
b1 ,
b1000111000000111110000111111110010101000100011111101101011111000000000000000000000000000000000000000000000000000000000000000000 #
b1000000 2
b11100 .
1"
#9850
0"
#9875
b1000000 -
b10 ,
b10001110000001111100001111111100101010001000111111011010111110000000000000000000000000000000000000000000000000000000000000000000 #
b1000000 2
b11100 .
1"
#9900
0"
#9925
b0 -
b11 ,
b11100000011111000011111111001010100010001111110110101111100000000000000000000000000000000000000000000000000000000000000000000 #
1$
b1000000 2
b11100 .
1"
#9950
0"
#9975
b1 -
b100 ,
b1 /
b111000000111110000111111110010101000100011111101101011111000000000000000000000000000000000000000000000000000000000000000000000 #
0$
b1000000 2
b11101 .
1"
#10000
0"
#10025
b10 -
b101 ,
b1 0
b0 /
b1110000001111100001111111100101010001000111111011010111110000000000000000000000000000000000000000000000000000000000000000000000 #
b1000000 2
b11101 .
1"
#10050
0"
#10075
b11 -
b110 ,
b0 0
b1 1
b11100000011111000011111111001010100010001111110110101111100000000000000000000000000000000000000000000000000000000000000000000000 #
b1000000 2
b11101 .
1"
#10100
0"
#10125
b100 -
b111 ,
b0 1
b11000000111110000111111110010101000100011111101101011111000000000000000000000000000000000000000000000000000000000000000000000000 #
1$
b1000000 2
b11110 .
1"
#10150
0"
#10175
b101 -
b1000 ,
b1 /
b10000001111100001111111100101010001000111111011010111110000000000000000000000000000000000000000000000000000000000000000000000000 #
b1000000 2
b11110 .
1"
#10200
0"
#10225
b110 -
b1001 ,
b1 0
b11111000011111111001010100010001111110110101111100000000000000000000000000000000000000000000000000000000000000000000000000 #
b1000000 2
b11111 .
1"
#10250
0"
#10275
b111 -
b1010 ,
b1 1
b111110000111111110010101000100011111101101011111000000000000000000000000000000000000000000000000000000000000000000000000000 #
0$
b1000000 2
b11111 .
1"
#10300
0"
#10325
b1000 -
b1011 ,
b0 /
b1111100001111111100101010001000111111011010111110000000000000000000000000000000000000000000000000000000000000000000000000000 #
b1000000 2
b11101 .
1"
#10350
0"
#10375
b1001 -
b1100 ,
b0 0
b11111000011111111001010100010001111110110101111100000000000000000000000000000000000000000000000000000000000000000000000000000 #
b1000000 2
b11101 .
1"
#10400
0"
#10425
b1010 -
b1101 ,
b0 1
b111110000111111110010101000100011111101101011111000000000000000000000000000000000000000000000000000000000000000000000000000000 #
b1000000 2
b11110 .
1"
#10450
0"
#10475
b1011 -
b1110 ,
b1111100001111111100101010001000111111011010111110000000000000000000000000000000000000000000000000000000000000000000000000000000 #
b1000000 2
b11110 .
1"
#10500
0"
#10525
b1100 -
b1111 ,
b11111000011111111001010100010001111110110101111100000000000000000000000000000000000000000000000000000000000000000000000000000000 #
b1000000 2
b11110 .
1"
#10550
0"
#10575
b1101 -
b10000 ,
b11110000111111110010101000100011111101101011111000000000000000000000000000000000000000000000000000000000000000000000000000000000 #
1$
b1000000 2
b11110 .
1"
#10600
0"
#10625
b1110 -
b10001 ,
b1 /
b11100001111111100101010001000111111011010111110000000000000000000000000000000000000000000000000000000000000000000000000000000000 #
b1000000 2
b11111 .
1"
#10650
0"
#10675
b1111 -
b1 +
b10010 ,
b1 0
b11000011111111001010100010001111110110101111100000000000000000000000000000000000000000000000000000000000000000000000000000000000 #
b1000000 2
b100000 .
1"
#10700
0"
#10725
b10000 -
b10011 ,
b1 1
b10000111111110010101000100011111101101011111000000000000000000000000000000000000000000000000000000000000000000000000000000000000 #
b1000000 2
b100000 .
1"
#10750
0"
#10775
b10001 -
b0 +
b10100 ,
b1111111100101010001000111111011010111110000000000000000000000000000000000000000000000000000000000000000000000000000000000000 #
b1000000 2
b11110 .
1"
#10800
0"
#10825
b10010 -
b10101 ,
b11111111001010100010001111110110101111100000000000000000000000000000000000000000000000000000000000000000000000000000000000000 #
0$
b1000000 2
b11101 .
1"
#10850
0"
#10875
b10011 -
b10110 ,
b0 /
b111111110010101000100011111101101011111000000000000000000000000000000000000000000000000000000000000000000000000000000000000000 #
b1000000 2
b11101 .
1"
#10900
0"
#10925
b10100 -
b10111 ,
b0 0
b1111111100101010001000111111011010111110000000000000000000000000000000000000000000000000000000000000000000000000000000000000000 #
b1000000 2
b11101 .
1"
#10950
0"
#10975
b10101 -
b11000 ,
b0 1
b11111111001010100010001111110110101111100000000000000000000000000000000000000000000000000000000000000000000000000000000000000000 #
b1000000 2
b11100 .
1"
#11000
0"
#11025
b10110 -
b11001 ,
b11111110010101000100011111101101011111000000000000000000000000000000000000000000000000000000000000000000000000000000000000000000 #
1$
b1000000 2
b11100 .
1"
#11050
0"
#11075
b10111 -
b11010 ,
b1 /
b11111100101010001000111111011010111110000000000000000000000000000000000000000000000000000000000000000000000000000000000000000000 #
b1000000 2
b11101 .
1"
#11100
0"
